messenger/__init__.py
messenger/bot.py
messenger/constant.py
messenger/helper/__init__.py
messenger/helper/utils.py
messenger/helper/http/__init__.py
messenger/helper/http/post.py
messenger/helper/http/prioritized_item.py
messenger/helper/http/request.py
messenger/helper/logging/__init__.py
messenger/helper/logging/log.py
messenger/helper/messaging/__init__.py
messenger/helper/messaging/attachment.py
messenger/helper/messaging/button.py
messenger/helper/messaging/button_template.py
messenger/helper/messaging/client_context.py
messenger/helper/messaging/element.py
messenger/helper/messaging/generic_template.py
messenger/helper/messaging/message.py
messenger/helper/messaging/message_template.py
messenger/helper/messaging/postback.py
messenger/helper/messaging/quick_reply.py
messenger/helper/messaging/receipt.py
messenger/helper/messaging/receipt_adjustment.py
messenger/helper/messaging/receipt_element.py
messenger/helper/messaging/response.py
python_messenger_bot-0.0.12.dist-info/LICENSE
python_messenger_bot-0.0.12.dist-info/METADATA
python_messenger_bot-0.0.12.dist-info/WHEEL
python_messenger_bot-0.0.12.dist-info/top_level.txt
python_messenger_bot-0.0.12.dist-info/RECORD
