Metadata-Version: 2.1
Name: python-messenger-bot
Version: 0.0.12
Summary: Wrapper for Facebook Messenger Platform (bot).
Home-page: https://github.com/gellowmellow/python-messenger-bot
Author: Gello Mark Vito
Author-email: gmcvito@gmail.com
License: UNKNOWN
Platform: UNKNOWN
Classifier: Programming Language :: Python :: 3
Classifier: License :: OSI Approved :: MIT License
Classifier: Operating System :: OS Independent
